LICENSE
README.md
setup.py
Ciper.egg-info/PKG-INFO
Ciper.egg-info/SOURCES.txt
Ciper.egg-info/dependency_links.txt
Ciper.egg-info/entry_points.txt
Ciper.egg-info/requires.txt
Ciper.egg-info/top_level.txt
ciper/__init__.py
ciper/ciper.py